adafruit_ds2413.py
adafruit_circuitpython_ds2413-1.2.22.dist-info/licenses/LICENSE
adafruit_circuitpython_ds2413-1.2.22.dist-info/METADATA
adafruit_circuitpython_ds2413-1.2.22.dist-info/WHEEL
adafruit_circuitpython_ds2413-1.2.22.dist-info/top_level.txt
adafruit_circuitpython_ds2413-1.2.22.dist-info/RECORD
