Metadata-Version: 2.4
Name: adafruit-circuitpython-ds2413
Version: 1.2.22
Summary: CircuitPython library for DS2413 1-Wire Dual Channel Addressable Switch.
Author-email: Adafruit Industries <circuitpython@adafruit.com>
License: MIT
Project-URL: Homepage, https://github.com/adafruit/Adafruit_CircuitPython_DS2413
Keywords: adafruit,haptic,motor,controller,buzzer,vibration,breakout,hardware,micropython,circuitpython
Classifier: Intended Audience :: Developers
Classifier: Topic :: Software Development :: Libraries
Classifier: Topic :: Software Development :: Embedded Systems
Classifier: Topic :: System :: Hardware
Classifier: License :: OSI Approved :: MIT License
Classifier: Programming Language :: Python :: 3
License-File: LICENSE
Requires-Dist: Adafruit-Blinka
Requires-Dist: adafruit-circuitpython-onewire
Requires-Dist: adafruit-circuitpython-busdevice
Requires-Dist: typing-extensions~=4.0
Provides-Extra: optional
Dynamic: license-file
